{"assets":{"1599450148-dbd9bca6":{"id":"1599450148-dbd9bca6","type":"texture","createdAt":"2020-09-07 11:42","modifiedAt":"2020-09-07 11:42","name":"10-16名称.png","preload":"true","has_thumbnail":true,"scope":{"type":"project","id":"a80566dc"},"file":{"filename":"10-16名称.png","size":18847,"hash":"26385d410baeebcbdd5170801b0dc05f7ffe33f9"},"data":null,"path":[]},"1599450148-44cb5081":{"id":"1599450148-44cb5081","type":"texture","createdAt":"2020-09-07 11:42","modifiedAt":"2020-09-07 11:42","name":"lock.png","preload":"true","has_thumbnail":true,"scope":{"type":"project","id":"a80566dc"},"file":{"filename":"lock.png","size":6673,"hash":"dcf1e14e97c835469f139a2f4a6ef14cbec81e21"},"data":null,"path":[]},"1599450148-86e783d0":{"id":"1599450148-86e783d0","type":"texture","createdAt":"2020-09-07 11:42","modifiedAt":"2020-09-07 11:42","name":"001VRay完成贴图.jpg","preload":"true","has_thumbnail":true,"scope":{"type":"project","id":"a80566dc"},"file":{"filename":"001VRay完成贴图.jpg","size":539395,"hash":"4736b34bda298337dac4600e5705475b3fb7f368"},"data":null,"path":[]},"1599450148-cab88031":{"id":"1599450148-cab88031","type":"texture","createdAt":"2020-09-07 11:42","modifiedAt":"2020-09-07 11:42","name":"标题.png","preload":"true","has_thumbnail":true,"scope":{"type":"project","id":"a80566dc"},"file":{"filename":"标题.png","size":17390,"hash":"5921c91e6e59ad4e6e3610c871da880e6b0ee2ef"},"data":null,"path":[]},"1599450148-a9f6fe16":{"id":"1599450148-a9f6fe16","type":"texture","createdAt":"2020-09-07 11:42","modifiedAt":"2020-09-07 11:42","name":"t_1.jpg","preload":"true","has_thumbnail":true,"scope":{"type":"project","id":"a80566dc"},"file":{"filename":"t_1.jpg","size":139828,"hash":"1b1d574211bb2813733cfc47a246e1a3e341d131"},"data":null,"path":[]},"1599450148-f399ee19":{"id":"1599450148-f399ee19","type":"texture","createdAt":"2020-09-07 11:42","modifiedAt":"2020-09-07 11:42","name":"电脑.jpg","preload":"true","has_thumbnail":true,"scope":{"type":"project","id":"a80566dc"},"file":{"filename":"电脑.jpg","size":45602,"hash":"f1d424378e73f8db515553d2bf2026be9117d69c"},"data":null,"path":[]},"1599450148-f1a63b16":{"id":"1599450148-f1a63b16","type":"texture","createdAt":"2020-09-07 11:42","modifiedAt":"2020-09-07 11:42","name":"对象184VRay完成贴图.jpg","preload":"true","has_thumbnail":true,"scope":{"type":"project","id":"a80566dc"},"file":{"filename":"对象184VRay完成贴图.jpg","size":248396,"hash":"d8346ebb8bc523135da3776334e6552c1e391220"},"data":null,"path":[]},"1599450148-80c84be0":{"id":"1599450148-80c84be0","type":"texture","createdAt":"2020-09-07 11:42","modifiedAt":"2020-09-07 11:42","name":"men.png","preload":"true","has_thumbnail":true,"scope":{"type":"project","id":"a80566dc"},"file":{"filename":"men.png","size":549205,"hash":"06a566fe6e71fef17559e5b1cd042d35e61bd108"},"data":null,"path":[]},"1599450148-8a725a25":{"id":"1599450148-8a725a25","type":"model","createdAt":"2020-09-07 11:42","modifiedAt":"2020-09-07 11:42","name":"F.babylon","preload":"true","has_thumbnail":false,"scope":{"type":"project","id":"a80566dc"},"file":{"filename":"F.babylon","size":1111694,"hash":"43cba531de4a56b838eabcc07c032cceecfc0f21"},"data":null,"path":[]},"1599450148-ac0936ff":{"id":"1599450148-ac0936ff","type":"material","createdAt":"2020-09-07 11:42","modifiedAt":"2020-09-07 11:42","name":"Material #37493","preload":false,"has_thumbnail":false,"scope":{"type":"project","id":"a80566dc"},"file":null,"data":{"customType":"BABYLON.StandardMaterial","ambient":[1,1,1],"diffuse":[1,1,1],"specular":[0,0,0],"emissive":[0,0,0],"specularPower":25.6,"diffuseTexture":{"name":"Line014VRay.jpg","level":1,"hasAlpha":true,"getAlphaFromRGB":false,"coordinatesMode":0,"isCube":false,"uOffset":0,"vOffset":0,"uScale":1,"vScale":-1,"uRotationCenter":0,"vRotationCenter":0,"wRotationCenter":0.5,"invertY":false,"uAng":0,"vAng":0,"wAng":0,"wrapU":1,"wrapV":1,"coordinatesIndex":0,"isRenderTarget":false,"renderTargetSize":0,"mirrorPlane":null,"renderList":null,"animations":[],"extensions":null,"samplingMode":3},"diffuseFresnelParameters":null,"ambientTexture":null,"opacityTexture":null,"opacityFresnelParameters":null,"reflectionTexture":null,"reflectionFresnelParameters":null,"emissiveTexture":null,"lightmapTexture":null,"useLightmapAsShadowmap":false,"emissiveFresnelParameters":null,"specularTexture":null,"bumpTexture":null,"useSpecularOverAlpha":true,"disableLighting":false,"useEmissiveAsIllumination":false,"linkEmissiveWithDiffuse":true,"twoSidedLighting":false,"maxSimultaneousLights":4,"useGlossinessFromSpecularMapAlpha":false,"name":"Material #37493","id":"db8b80e6-b96a-4916-902b-8278a716d828","backFaceCulling":true,"wireframe":false,"alpha":1,"alphaMode":2},"path":[]},"1599450148-4ee9e685":{"id":"1599450148-4ee9e685","type":"material","createdAt":"2020-09-07 11:42","modifiedAt":"2020-09-07 11:42","name":"F-ground","preload":false,"has_thumbnail":false,"scope":{"type":"project","id":"a80566dc"},"file":null,"data":{"customType":"BABYLON.StandardMaterial","ambient":[1,1,1],"diffuse":[1,1,1],"specular":[0,0,0],"emissive":[0,0,0],"specularPower":25.6,"diffuseTexture":{"name":"对象199VRay完成贴图.jpg","level":1,"hasAlpha":true,"getAlphaFromRGB":false,"coordinatesMode":0,"isCube":false,"uOffset":0,"vOffset":0,"uScale":1,"vScale":-1,"uRotationCenter":0,"vRotationCenter":0,"wRotationCenter":0.5,"invertY":false,"uAng":0,"vAng":0,"wAng":0,"wrapU":1,"wrapV":1,"coordinatesIndex":0,"isRenderTarget":false,"renderTargetSize":0,"mirrorPlane":null,"renderList":null,"animations":[],"extensions":null,"samplingMode":3},"diffuseFresnelParameters":null,"ambientTexture":null,"opacityTexture":null,"opacityFresnelParameters":null,"reflectionTexture":null,"reflectionFresnelParameters":null,"emissiveTexture":null,"lightmapTexture":null,"useLightmapAsShadowmap":false,"emissiveFresnelParameters":null,"specularTexture":null,"bumpTexture":null,"useSpecularOverAlpha":true,"disableLighting":false,"useEmissiveAsIllumination":false,"linkEmissiveWithDiffuse":true,"twoSidedLighting":false,"maxSimultaneousLights":4,"useGlossinessFromSpecularMapAlpha":false,"name":"F-ground","id":"abde4946-d763-453b-af3e-c11a5e2acab8","backFaceCulling":true,"wireframe":false,"alpha":1,"alphaMode":2},"path":[]},"1599450148-aed09ab7":{"id":"1599450148-aed09ab7","type":"material","createdAt":"2020-09-07 11:42","modifiedAt":"2020-09-07 11:42","name":"Material #3194","preload":false,"has_thumbnail":false,"scope":{"type":"project","id":"a80566dc"},"file":null,"data":{"customType":"BABYLON.StandardMaterial","ambient":[1,1,1],"diffuse":[1,1,1],"specular":[0,0,0],"emissive":[0,0,0],"specularPower":25.6,"diffuseTexture":{"name":"电脑.jpg","level":1,"hasAlpha":true,"getAlphaFromRGB":false,"coordinatesMode":0,"isCube":false,"uOffset":0,"vOffset":0,"uScale":1,"vScale":-1,"uRotationCenter":0,"vRotationCenter":0,"wRotationCenter":0.5,"invertY":false,"uAng":0,"vAng":0,"wAng":0,"wrapU":1,"wrapV":1,"coordinatesIndex":0,"isRenderTarget":false,"renderTargetSize":0,"mirrorPlane":null,"renderList":null,"animations":[],"extensions":null,"samplingMode":3,"texture_id":"1599450148-f399ee19"},"diffuseFresnelParameters":null,"ambientTexture":null,"opacityTexture":null,"opacityFresnelParameters":null,"reflectionTexture":null,"reflectionFresnelParameters":null,"emissiveTexture":null,"lightmapTexture":null,"useLightmapAsShadowmap":false,"emissiveFresnelParameters":null,"specularTexture":null,"bumpTexture":null,"useSpecularOverAlpha":true,"disableLighting":false,"useEmissiveAsIllumination":false,"linkEmissiveWithDiffuse":true,"twoSidedLighting":false,"maxSimultaneousLights":4,"useGlossinessFromSpecularMapAlpha":false,"name":"Material #3194","id":"33a181c9-5d4b-46a3-8f57-cd45ab54f380","backFaceCulling":true,"wireframe":false,"alpha":1,"alphaMode":2},"path":[]},"1599450148-a17af9d5":{"id":"1599450148-a17af9d5","type":"material","createdAt":"2020-09-07 11:42","modifiedAt":"2020-09-07 11:42","name":"Material #37518","preload":false,"has_thumbnail":false,"scope":{"type":"project","id":"a80566dc"},"file":null,"data":{"customType":"BABYLON.StandardMaterial","ambient":[1,1,1],"diffuse":[1,1,1],"specular":[0,0,0],"emissive":[0,0,0],"specularPower":25.6,"diffuseTexture":{"name":"001VRay完成贴图.jpg","level":1,"hasAlpha":true,"getAlphaFromRGB":false,"coordinatesMode":0,"isCube":false,"uOffset":0,"vOffset":0,"uScale":1,"vScale":-1,"uRotationCenter":0,"vRotationCenter":0,"wRotationCenter":0.5,"invertY":false,"uAng":0,"vAng":0,"wAng":0,"wrapU":1,"wrapV":1,"coordinatesIndex":0,"isRenderTarget":false,"renderTargetSize":0,"mirrorPlane":null,"renderList":null,"animations":[],"extensions":null,"samplingMode":3,"texture_id":"1599450148-86e783d0"},"diffuseFresnelParameters":null,"ambientTexture":null,"opacityTexture":null,"opacityFresnelParameters":null,"reflectionTexture":null,"reflectionFresnelParameters":null,"emissiveTexture":null,"lightmapTexture":null,"useLightmapAsShadowmap":false,"emissiveFresnelParameters":null,"specularTexture":null,"bumpTexture":null,"useSpecularOverAlpha":true,"disableLighting":false,"useEmissiveAsIllumination":false,"linkEmissiveWithDiffuse":true,"twoSidedLighting":false,"maxSimultaneousLights":4,"useGlossinessFromSpecularMapAlpha":false,"name":"Material #37518","id":"ec871578-9f6b-4d46-b939-5872bf1f0fd1","backFaceCulling":true,"wireframe":false,"alpha":1,"alphaMode":2},"path":[]},"1599450148-880019e6":{"id":"1599450148-880019e6","type":"material","createdAt":"2020-09-07 11:42","modifiedAt":"2020-09-07 11:42","name":"Material #37519","preload":false,"has_thumbnail":false,"scope":{"type":"project","id":"a80566dc"},"file":null,"data":{"customType":"BABYLON.StandardMaterial","ambient":[1,1,1],"diffuse":[1,1,1],"specular":[0,0,0],"emissive":[0,0,0],"specularPower":25.6,"diffuseTexture":{"name":"t_1.jpg","level":1,"hasAlpha":true,"getAlphaFromRGB":false,"coordinatesMode":0,"isCube":false,"uOffset":0,"vOffset":0,"uScale":1,"vScale":-1,"uRotationCenter":0,"vRotationCenter":0,"wRotationCenter":0.5,"invertY":false,"uAng":0,"vAng":0,"wAng":0,"wrapU":1,"wrapV":1,"coordinatesIndex":0,"isRenderTarget":false,"renderTargetSize":0,"mirrorPlane":null,"renderList":null,"animations":[],"extensions":null,"samplingMode":3,"texture_id":"1599450148-a9f6fe16"},"diffuseFresnelParameters":null,"ambientTexture":null,"opacityTexture":null,"opacityFresnelParameters":null,"reflectionTexture":null,"reflectionFresnelParameters":null,"emissiveTexture":null,"lightmapTexture":null,"useLightmapAsShadowmap":false,"emissiveFresnelParameters":null,"specularTexture":null,"bumpTexture":null,"useSpecularOverAlpha":true,"disableLighting":false,"useEmissiveAsIllumination":false,"linkEmissiveWithDiffuse":true,"twoSidedLighting":false,"maxSimultaneousLights":4,"useGlossinessFromSpecularMapAlpha":false,"name":"Material #37519","id":"db03fe9c-4e74-4b37-80db-64256f0b93a5","backFaceCulling":true,"wireframe":false,"alpha":1,"alphaMode":2},"path":[]},"1599450148-bc23834d":{"id":"1599450148-bc23834d","type":"material","createdAt":"2020-09-07 11:42","modifiedAt":"2020-09-07 11:42","name":"Material #2147448229","preload":false,"has_thumbnail":false,"scope":{"type":"project","id":"a80566dc"},"file":null,"data":{"customType":"BABYLON.StandardMaterial","ambient":[1,1,1],"diffuse":[1,1,1],"specular":[0,0,0],"emissive":[0,0,0],"specularPower":25.6,"diffuseTexture":{"name":"展厅XX主题 .png","level":1,"hasAlpha":true,"getAlphaFromRGB":false,"coordinatesMode":0,"isCube":false,"uOffset":0,"vOffset":0,"uScale":1,"vScale":-1,"uRotationCenter":0,"vRotationCenter":0,"wRotationCenter":0.5,"invertY":false,"uAng":0,"vAng":0,"wAng":0,"wrapU":1,"wrapV":1,"coordinatesIndex":0,"isRenderTarget":false,"renderTargetSize":0,"mirrorPlane":null,"renderList":null,"animations":[],"extensions":null,"samplingMode":3},"diffuseFresnelParameters":null,"ambientTexture":null,"opacityTexture":null,"opacityFresnelParameters":null,"reflectionTexture":null,"reflectionFresnelParameters":null,"emissiveTexture":null,"lightmapTexture":null,"useLightmapAsShadowmap":false,"emissiveFresnelParameters":null,"specularTexture":null,"bumpTexture":null,"useSpecularOverAlpha":true,"disableLighting":false,"useEmissiveAsIllumination":false,"linkEmissiveWithDiffuse":true,"twoSidedLighting":false,"maxSimultaneousLights":4,"useGlossinessFromSpecularMapAlpha":false,"name":"Material #2147448229","id":"b4b32d90-b143-458b-b9fc-9a647f17e273","backFaceCulling":true,"wireframe":false,"alpha":1,"alphaMode":2},"path":[]},"1599450148-eb3c9d3b":{"id":"1599450148-eb3c9d3b","type":"material","createdAt":"2020-09-07 11:42","modifiedAt":"2020-09-07 11:42","name":"画_10-16","preload":false,"has_thumbnail":false,"scope":{"type":"project","id":"a80566dc"},"file":null,"data":{"customType":"BABYLON.StandardMaterial","ambient":[1,1,1],"diffuse":[1,1,1],"specular":[0,0,0],"emissive":[0,0,0],"specularPower":25.6,"diffuseTexture":{"name":"展画.jpg","level":1,"hasAlpha":true,"getAlphaFromRGB":false,"coordinatesMode":0,"isCube":false,"uOffset":0,"vOffset":0,"uScale":1,"vScale":-1,"uRotationCenter":0,"vRotationCenter":0,"wRotationCenter":0.5,"invertY":false,"uAng":0,"vAng":0,"wAng":0,"wrapU":1,"wrapV":1,"coordinatesIndex":0,"isRenderTarget":false,"renderTargetSize":0,"mirrorPlane":null,"renderList":null,"animations":[],"extensions":null,"samplingMode":3,"texture_id":"1599450148-6d7963d8"},"diffuseFresnelParameters":null,"ambientTexture":null,"opacityTexture":null,"opacityFresnelParameters":null,"reflectionTexture":null,"reflectionFresnelParameters":null,"emissiveTexture":null,"lightmapTexture":null,"useLightmapAsShadowmap":false,"emissiveFresnelParameters":null,"specularTexture":null,"bumpTexture":null,"useSpecularOverAlpha":true,"disableLighting":false,"useEmissiveAsIllumination":false,"linkEmissiveWithDiffuse":true,"twoSidedLighting":false,"maxSimultaneousLights":4,"useGlossinessFromSpecularMapAlpha":false,"name":"画_10-16","id":"216484dc-9e8d-42f3-b01d-4b82d97a3b3c","backFaceCulling":true,"wireframe":false,"alpha":1,"alphaMode":2},"path":[]},"1599450148-ffada7f0":{"id":"1599450148-ffada7f0","type":"material","createdAt":"2020-09-07 11:42","modifiedAt":"2020-09-07 11:42","name":"16名称","preload":false,"has_thumbnail":false,"scope":{"type":"project","id":"a80566dc"},"file":null,"data":{"customType":"BABYLON.StandardMaterial","ambient":[1,1,1],"diffuse":[1,1,1],"specular":[0,0,0],"emissive":[0,0,0],"specularPower":25.6,"diffuseTexture":{"name":"标题.png","level":1,"hasAlpha":true,"getAlphaFromRGB":false,"coordinatesMode":0,"isCube":false,"uOffset":0,"vOffset":0,"uScale":1,"vScale":-1,"uRotationCenter":0,"vRotationCenter":0,"wRotationCenter":0.5,"invertY":false,"uAng":0,"vAng":0,"wAng":0,"wrapU":1,"wrapV":1,"coordinatesIndex":0,"isRenderTarget":false,"renderTargetSize":0,"mirrorPlane":null,"renderList":null,"animations":[],"extensions":null,"samplingMode":3,"texture_id":"1599450148-cab88031"},"diffuseFresnelParameters":null,"ambientTexture":null,"opacityTexture":{"name":"10-16名称.png","level":1,"hasAlpha":true,"getAlphaFromRGB":false,"coordinatesMode":0,"isCube":false,"uOffset":0,"vOffset":0,"uScale":1,"vScale":-1,"uRotationCenter":0,"vRotationCenter":0,"wRotationCenter":0.5,"invertY":false,"uAng":0,"vAng":0,"wAng":0,"wrapU":1,"wrapV":1,"coordinatesIndex":0,"isRenderTarget":false,"renderTargetSize":0,"mirrorPlane":null,"renderList":null,"animations":[],"extensions":null,"samplingMode":3,"texture_id":"1599450148-dbd9bca6"},"opacityFresnelParameters":null,"reflectionTexture":null,"reflectionFresnelParameters":null,"emissiveTexture":null,"lightmapTexture":null,"useLightmapAsShadowmap":false,"emissiveFresnelParameters":null,"specularTexture":null,"bumpTexture":null,"useSpecularOverAlpha":true,"disableLighting":false,"useEmissiveAsIllumination":false,"linkEmissiveWithDiffuse":true,"twoSidedLighting":false,"maxSimultaneousLights":4,"useGlossinessFromSpecularMapAlpha":false,"name":"16名称","id":"adc5b7c2-fbaa-44ed-a64a-567a52519692","backFaceCulling":true,"wireframe":false,"alpha":1,"alphaMode":2},"path":[]},"1599450148-427b03fe":{"id":"1599450148-427b03fe","type":"material","createdAt":"2020-09-07 11:42","modifiedAt":"2020-09-07 11:42","name":"Material #2147448150","preload":false,"has_thumbnail":false,"scope":{"type":"project","id":"a80566dc"},"file":null,"data":{"customType":"BABYLON.StandardMaterial","ambient":[0.3765,0.5059,0.5882],"diffuse":[0.3765,0.5059,0.5882],"specular":[0,0,0],"emissive":[0,0,0],"specularPower":25.6,"diffuseTexture":null,"diffuseFresnelParameters":null,"ambientTexture":null,"opacityTexture":null,"opacityFresnelParameters":null,"reflectionTexture":null,"reflectionFresnelParameters":null,"emissiveTexture":null,"lightmapTexture":null,"useLightmapAsShadowmap":false,"emissiveFresnelParameters":null,"specularTexture":null,"bumpTexture":null,"useSpecularOverAlpha":true,"disableLighting":false,"useEmissiveAsIllumination":false,"linkEmissiveWithDiffuse":true,"twoSidedLighting":false,"maxSimultaneousLights":4,"useGlossinessFromSpecularMapAlpha":false,"name":"Material #2147448150","id":"db5a01d2-421d-4cea-9074-4c22285d14c7","backFaceCulling":true,"wireframe":false,"alpha":0,"alphaMode":2},"path":[]},"1599450148-6f74be2f":{"id":"1599450148-6f74be2f","type":"material","createdAt":"2020-09-07 11:42","modifiedAt":"2020-09-07 11:42","name":"men","preload":false,"has_thumbnail":false,"scope":{"type":"project","id":"a80566dc"},"file":null,"data":{"customType":"BABYLON.StandardMaterial","ambient":[0.3765,0.5059,0.5882],"diffuse":[1,1,1],"specular":[0,0,0],"emissive":[0,0,0],"specularPower":25.6,"diffuseTexture":{"name":"men.png","level":1,"hasAlpha":true,"getAlphaFromRGB":false,"coordinatesMode":0,"isCube":false,"uOffset":0,"vOffset":0,"uScale":1,"vScale":-1,"uRotationCenter":0,"vRotationCenter":0,"wRotationCenter":0.5,"invertY":false,"uAng":0,"vAng":0,"wAng":0,"wrapU":1,"wrapV":1,"coordinatesIndex":0,"isRenderTarget":false,"renderTargetSize":0,"mirrorPlane":null,"renderList":null,"animations":[],"extensions":null,"samplingMode":3,"texture_id":"1599450148-80c84be0"},"diffuseFresnelParameters":null,"ambientTexture":null,"opacityTexture":null,"opacityFresnelParameters":null,"reflectionTexture":null,"reflectionFresnelParameters":null,"emissiveTexture":null,"lightmapTexture":null,"useLightmapAsShadowmap":false,"emissiveFresnelParameters":null,"specularTexture":null,"bumpTexture":null,"useSpecularOverAlpha":true,"disableLighting":false,"useEmissiveAsIllumination":false,"linkEmissiveWithDiffuse":true,"twoSidedLighting":false,"maxSimultaneousLights":4,"useGlossinessFromSpecularMapAlpha":false,"name":"men","id":"49de277a-c3b4-44c1-9ed1-fab4b0c9a5e8","backFaceCulling":true,"wireframe":false,"alpha":1,"alphaMode":2},"path":[]},"1599450148-9a03d077":{"id":"1599450148-9a03d077","type":"material","createdAt":"2020-09-07 11:42","modifiedAt":"2020-09-07 11:42","name":"透明玻璃","preload":false,"has_thumbnail":false,"scope":{"type":"project","id":"a80566dc"},"file":null,"data":{"customType":"BABYLON.StandardMaterial","ambient":[0.0784,0.0784,0.0784],"diffuse":[0.0784,0.0784,0.0784],"specular":[0,0,0],"emissive":[0,0,0],"specularPower":25.6,"diffuseTexture":null,"diffuseFresnelParameters":null,"ambientTexture":null,"opacityTexture":null,"opacityFresnelParameters":null,"reflectionTexture":null,"reflectionFresnelParameters":null,"emissiveTexture":null,"lightmapTexture":null,"useLightmapAsShadowmap":false,"emissiveFresnelParameters":null,"specularTexture":null,"bumpTexture":null,"useSpecularOverAlpha":true,"disableLighting":false,"useEmissiveAsIllumination":false,"linkEmissiveWithDiffuse":true,"twoSidedLighting":false,"maxSimultaneousLights":4,"useGlossinessFromSpecularMapAlpha":false,"name":"透明玻璃","id":"460162c2-4464-4997-991b-9b8bc47ef392","backFaceCulling":true,"wireframe":false,"alpha":0,"alphaMode":2},"path":[]},"1599450148-d6986f0a":{"id":"1599450148-d6986f0a","type":"material","createdAt":"2020-09-07 11:42","modifiedAt":"2020-09-07 11:42","name":"Material #6278","preload":false,"has_thumbnail":false,"scope":{"type":"project","id":"a80566dc"},"file":null,"data":{"customType":"BABYLON.StandardMaterial","ambient":[1,1,1],"diffuse":[1,1,1],"specular":[0,0,0],"emissive":[1,1,1],"specularPower":25.6,"diffuseTexture":null,"diffuseFresnelParameters":null,"ambientTexture":null,"opacityTexture":null,"opacityFresnelParameters":null,"reflectionTexture":null,"reflectionFresnelParameters":null,"emissiveTexture":null,"lightmapTexture":null,"useLightmapAsShadowmap":false,"emissiveFresnelParameters":null,"specularTexture":null,"bumpTexture":null,"useSpecularOverAlpha":true,"disableLighting":false,"useEmissiveAsIllumination":true,"linkEmissiveWithDiffuse":false,"twoSidedLighting":false,"maxSimultaneousLights":4,"useGlossinessFromSpecularMapAlpha":false,"name":"Material #6278","id":"73e53886-ec5a-4c39-b06f-ffdd5f9dd75d","backFaceCulling":true,"wireframe":false,"alpha":0,"alphaMode":2},"path":[]},"1599450148-2c6f003c":{"id":"1599450148-2c6f003c","type":"material","createdAt":"2020-09-07 11:42","modifiedAt":"2020-09-07 11:42","name":"Material #2147448218","preload":false,"has_thumbnail":false,"scope":{"type":"project","id":"a80566dc"},"file":null,"data":{"customType":"BABYLON.StandardMaterial","ambient":[1,1,1],"diffuse":[1,1,1],"specular":[0,0,0],"emissive":[0,0,0],"specularPower":25.6,"diffuseTexture":{"name":"lock.png","level":1,"hasAlpha":true,"getAlphaFromRGB":false,"coordinatesMode":0,"isCube":false,"uOffset":0,"vOffset":0,"uScale":1,"vScale":-1,"uRotationCenter":0,"vRotationCenter":0,"wRotationCenter":0.5,"invertY":false,"uAng":0,"vAng":0,"wAng":0,"wrapU":1,"wrapV":1,"coordinatesIndex":0,"isRenderTarget":false,"renderTargetSize":0,"mirrorPlane":null,"renderList":null,"animations":[],"extensions":null,"samplingMode":3,"texture_id":"1599450148-44cb5081"},"diffuseFresnelParameters":null,"ambientTexture":null,"opacityTexture":null,"opacityFresnelParameters":null,"reflectionTexture":null,"reflectionFresnelParameters":null,"emissiveTexture":null,"lightmapTexture":null,"useLightmapAsShadowmap":false,"emissiveFresnelParameters":null,"specularTexture":null,"bumpTexture":null,"useSpecularOverAlpha":true,"disableLighting":false,"useEmissiveAsIllumination":false,"linkEmissiveWithDiffuse":true,"twoSidedLighting":false,"maxSimultaneousLights":4,"useGlossinessFromSpecularMapAlpha":false,"name":"Material #2147448218","id":"5cb5574f-83b6-4749-8d19-f5a58a7521d2","backFaceCulling":true,"wireframe":false,"alpha":1,"alphaMode":2},"path":[]},"1599450148-daa74482":{"id":"1599450148-daa74482","type":"material","createdAt":"2020-09-07 11:42","modifiedAt":"2020-09-07 11:42","name":"Material #37494","preload":false,"has_thumbnail":false,"scope":{"type":"project","id":"a80566dc"},"file":null,"data":{"customType":"BABYLON.StandardMaterial","ambient":[1,1,1],"diffuse":[1,1,1],"specular":[0,0,0],"emissive":[0,0,0],"specularPower":25.6,"diffuseTexture":{"name":"对象184VRay完成贴图.jpg","level":1,"hasAlpha":true,"getAlphaFromRGB":false,"coordinatesMode":0,"isCube":false,"uOffset":0,"vOffset":0,"uScale":1,"vScale":-1,"uRotationCenter":0,"vRotationCenter":0,"wRotationCenter":0.5,"invertY":false,"uAng":0,"vAng":0,"wAng":0,"wrapU":1,"wrapV":1,"coordinatesIndex":0,"isRenderTarget":false,"renderTargetSize":0,"mirrorPlane":null,"renderList":null,"animations":[],"extensions":null,"samplingMode":3,"texture_id":"1599450148-f1a63b16"},"diffuseFresnelParameters":null,"ambientTexture":null,"opacityTexture":null,"opacityFresnelParameters":null,"reflectionTexture":null,"reflectionFresnelParameters":null,"emissiveTexture":null,"lightmapTexture":null,"useLightmapAsShadowmap":false,"emissiveFresnelParameters":null,"specularTexture":null,"bumpTexture":null,"useSpecularOverAlpha":true,"disableLighting":false,"useEmissiveAsIllumination":false,"linkEmissiveWithDiffuse":true,"twoSidedLighting":false,"maxSimultaneousLights":4,"useGlossinessFromSpecularMapAlpha":false,"name":"Material #37494","id":"c0faf073-2dc8-43b3-b722-ba01c8a6279a","backFaceCulling":true,"wireframe":false,"alpha":1,"alphaMode":2},"path":[]},"1599450148-6d7963d8":{"id":"1599450148-6d7963d8","type":"texture","createdAt":"2020-09-07 11:42","modifiedAt":"2020-09-07 11:42","name":"展画.jpg","preload":"true","has_thumbnail":true,"scope":{"type":"project","id":"a80566dc"},"file":{"filename":"展画.jpg","size":1365831,"hash":"33467df275d97be10ad7b38a72f7360ffb729cff"},"data":null,"path":[]},"1599556223-b4e09e09":{"id":"1599556223-b4e09e09","type":"folder","createdAt":"2020-09-08 17:10","modifiedAt":"2020-09-08 17:10","name":"新建文件夹","preload":"false","has_thumbnail":false,"scope":{"type":"project","id":"a80566dc"},"file":null,"data":null,"path":[]},"1599556231-4a198978":{"id":"1599556231-4a198978","type":"texture","createdAt":"2020-09-08 17:10","modifiedAt":"2020-09-08 17:10","name":"10-16名称.png","preload":"true","has_thumbnail":true,"scope":{"type":"project","id":"a80566dc"},"file":{"filename":"10-16名称.png","size":18847,"hash":"26385d410baeebcbdd5170801b0dc05f7ffe33f9"},"data":null,"path":["1599556223-b4e09e09"]},"1599556231-c18733cc":{"id":"1599556231-c18733cc","type":"texture","createdAt":"2020-09-08 17:10","modifiedAt":"2020-09-08 17:10","name":"lock.png","preload":"true","has_thumbnail":true,"scope":{"type":"project","id":"a80566dc"},"file":{"filename":"lock.png","size":6673,"hash":"dcf1e14e97c835469f139a2f4a6ef14cbec81e21"},"data":null,"path":["1599556223-b4e09e09"]},"1599556231-7992c2e9":{"id":"1599556231-7992c2e9","type":"texture","createdAt":"2020-09-08 17:10","modifiedAt":"2020-09-08 17:10","name":"001VRay完成贴图.jpg","preload":"true","has_thumbnail":true,"scope":{"type":"project","id":"a80566dc"},"file":{"filename":"001VRay完成贴图.jpg","size":539395,"hash":"4736b34bda298337dac4600e5705475b3fb7f368"},"data":null,"path":["1599556223-b4e09e09"]},"1599556231-bf26edb9":{"id":"1599556231-bf26edb9","type":"texture","createdAt":"2020-09-08 17:10","modifiedAt":"2020-09-08 17:10","name":"t_1.jpg","preload":"true","has_thumbnail":true,"scope":{"type":"project","id":"a80566dc"},"file":{"filename":"t_1.jpg","size":139828,"hash":"1b1d574211bb2813733cfc47a246e1a3e341d131"},"data":null,"path":["1599556223-b4e09e09"]},"1599556231-63e2ef8a":{"id":"1599556231-63e2ef8a","type":"texture","createdAt":"2020-09-08 17:10","modifiedAt":"2020-09-08 17:10","name":"标题.png","preload":"true","has_thumbnail":true,"scope":{"type":"project","id":"a80566dc"},"file":{"filename":"标题.png","size":17390,"hash":"5921c91e6e59ad4e6e3610c871da880e6b0ee2ef"},"data":null,"path":["1599556223-b4e09e09"]},"1599556231-316f2e8d":{"id":"1599556231-316f2e8d","type":"texture","createdAt":"2020-09-08 17:10","modifiedAt":"2020-09-08 17:10","name":"电脑.jpg","preload":"true","has_thumbnail":true,"scope":{"type":"project","id":"a80566dc"},"file":{"filename":"电脑.jpg","size":45602,"hash":"f1d424378e73f8db515553d2bf2026be9117d69c"},"data":null,"path":["1599556223-b4e09e09"]},"1599556231-e5de7b0f":{"id":"1599556231-e5de7b0f","type":"texture","createdAt":"2020-09-08 17:10","modifiedAt":"2020-09-08 17:10","name":"men.png","preload":"true","has_thumbnail":true,"scope":{"type":"project","id":"a80566dc"},"file":{"filename":"men.png","size":549205,"hash":"06a566fe6e71fef17559e5b1cd042d35e61bd108"},"data":null,"path":["1599556223-b4e09e09"]},"1599556231-66c8b544":{"id":"1599556231-66c8b544","type":"texture","createdAt":"2020-09-08 17:10","modifiedAt":"2020-09-08 17:10","name":"对象184VRay完成贴图.jpg","preload":"true","has_thumbnail":true,"scope":{"type":"project","id":"a80566dc"},"file":{"filename":"对象184VRay完成贴图.jpg","size":248396,"hash":"d8346ebb8bc523135da3776334e6552c1e391220"},"data":null,"path":["1599556223-b4e09e09"]},"1599556231-4830bac7":{"id":"1599556231-4830bac7","type":"model","createdAt":"2020-09-08 17:10","modifiedAt":"2020-09-08 17:10","name":"F.babylon","preload":"true","has_thumbnail":false,"scope":{"type":"project","id":"a80566dc"},"file":{"filename":"F.babylon","size":1111694,"hash":"43cba531de4a56b838eabcc07c032cceecfc0f21"},"data":null,"path":["1599556223-b4e09e09"]},"1599556231-afee3f08":{"id":"1599556231-afee3f08","type":"material","createdAt":"2020-09-08 17:10","modifiedAt":"2020-09-08 17:10","name":"Material #37493","preload":false,"has_thumbnail":false,"scope":{"type":"project","id":"a80566dc"},"file":null,"data":{"customType":"BABYLON.StandardMaterial","ambient":[1,1,1],"diffuse":[1,1,1],"specular":[0,0,0],"emissive":[0,0,0],"specularPower":25.6,"diffuseTexture":{"name":"Line014VRay.jpg","level":1,"hasAlpha":true,"getAlphaFromRGB":false,"coordinatesMode":0,"isCube":false,"uOffset":0,"vOffset":0,"uScale":1,"vScale":-1,"uRotationCenter":0,"vRotationCenter":0,"wRotationCenter":0.5,"invertY":false,"uAng":0,"vAng":0,"wAng":0,"wrapU":1,"wrapV":1,"coordinatesIndex":0,"isRenderTarget":false,"renderTargetSize":0,"mirrorPlane":null,"renderList":null,"animations":[],"extensions":null,"samplingMode":3},"diffuseFresnelParameters":null,"ambientTexture":null,"opacityTexture":null,"opacityFresnelParameters":null,"reflectionTexture":null,"reflectionFresnelParameters":null,"emissiveTexture":null,"lightmapTexture":null,"useLightmapAsShadowmap":false,"emissiveFresnelParameters":null,"specularTexture":null,"bumpTexture":null,"useSpecularOverAlpha":true,"disableLighting":false,"useEmissiveAsIllumination":false,"linkEmissiveWithDiffuse":true,"twoSidedLighting":false,"maxSimultaneousLights":4,"useGlossinessFromSpecularMapAlpha":false,"name":"Material #37493","id":"db8b80e6-b96a-4916-902b-8278a716d828","backFaceCulling":true,"wireframe":false,"alpha":1,"alphaMode":2},"path":["1599556223-b4e09e09"]},"1599556231-59fe6175":{"id":"1599556231-59fe6175","type":"material","createdAt":"2020-09-08 17:10","modifiedAt":"2020-09-08 17:10","name":"F-ground","preload":false,"has_thumbnail":false,"scope":{"type":"project","id":"a80566dc"},"file":null,"data":{"customType":"BABYLON.StandardMaterial","ambient":[1,1,1],"diffuse":[1,1,1],"specular":[0,0,0],"emissive":[0,0,0],"specularPower":25.6,"diffuseTexture":{"name":"对象199VRay完成贴图.jpg","level":1,"hasAlpha":true,"getAlphaFromRGB":false,"coordinatesMode":0,"isCube":false,"uOffset":0,"vOffset":0,"uScale":1,"vScale":-1,"uRotationCenter":0,"vRotationCenter":0,"wRotationCenter":0.5,"invertY":false,"uAng":0,"vAng":0,"wAng":0,"wrapU":1,"wrapV":1,"coordinatesIndex":0,"isRenderTarget":false,"renderTargetSize":0,"mirrorPlane":null,"renderList":null,"animations":[],"extensions":null,"samplingMode":3},"diffuseFresnelParameters":null,"ambientTexture":null,"opacityTexture":null,"opacityFresnelParameters":null,"reflectionTexture":null,"reflectionFresnelParameters":null,"emissiveTexture":null,"lightmapTexture":null,"useLightmapAsShadowmap":false,"emissiveFresnelParameters":null,"specularTexture":null,"bumpTexture":null,"useSpecularOverAlpha":true,"disableLighting":false,"useEmissiveAsIllumination":false,"linkEmissiveWithDiffuse":true,"twoSidedLighting":false,"maxSimultaneousLights":4,"useGlossinessFromSpecularMapAlpha":false,"name":"F-ground","id":"abde4946-d763-453b-af3e-c11a5e2acab8","backFaceCulling":true,"wireframe":false,"alpha":1,"alphaMode":2},"path":["1599556223-b4e09e09"]},"1599556231-d11ba66a":{"id":"1599556231-d11ba66a","type":"material","createdAt":"2020-09-08 17:10","modifiedAt":"2020-09-08 17:10","name":"Material #3194","preload":false,"has_thumbnail":false,"scope":{"type":"project","id":"a80566dc"},"file":null,"data":{"customType":"BABYLON.StandardMaterial","ambient":[1,1,1],"diffuse":[1,1,1],"specular":[0,0,0],"emissive":[0,0,0],"specularPower":25.6,"diffuseTexture":{"name":"电脑.jpg","level":1,"hasAlpha":true,"getAlphaFromRGB":false,"coordinatesMode":0,"isCube":false,"uOffset":0,"vOffset":0,"uScale":1,"vScale":-1,"uRotationCenter":0,"vRotationCenter":0,"wRotationCenter":0.5,"invertY":false,"uAng":0,"vAng":0,"wAng":0,"wrapU":1,"wrapV":1,"coordinatesIndex":0,"isRenderTarget":false,"renderTargetSize":0,"mirrorPlane":null,"renderList":null,"animations":[],"extensions":null,"samplingMode":3,"texture_id":"1599556231-316f2e8d"},"diffuseFresnelParameters":null,"ambientTexture":null,"opacityTexture":null,"opacityFresnelParameters":null,"reflectionTexture":null,"reflectionFresnelParameters":null,"emissiveTexture":null,"lightmapTexture":null,"useLightmapAsShadowmap":false,"emissiveFresnelParameters":null,"specularTexture":null,"bumpTexture":null,"useSpecularOverAlpha":true,"disableLighting":false,"useEmissiveAsIllumination":false,"linkEmissiveWithDiffuse":true,"twoSidedLighting":false,"maxSimultaneousLights":4,"useGlossinessFromSpecularMapAlpha":false,"name":"Material #3194","id":"33a181c9-5d4b-46a3-8f57-cd45ab54f380","backFaceCulling":true,"wireframe":false,"alpha":1,"alphaMode":2},"path":["1599556223-b4e09e09"]},"1599556231-1d616460":{"id":"1599556231-1d616460","type":"material","createdAt":"2020-09-08 17:10","modifiedAt":"2020-09-08 17:10","name":"Material #37518","preload":false,"has_thumbnail":false,"scope":{"type":"project","id":"a80566dc"},"file":null,"data":{"customType":"BABYLON.StandardMaterial","ambient":[1,1,1],"diffuse":[1,1,1],"specular":[0,0,0],"emissive":[0,0,0],"specularPower":25.6,"diffuseTexture":{"name":"001VRay完成贴图.jpg","level":1,"hasAlpha":true,"getAlphaFromRGB":false,"coordinatesMode":0,"isCube":false,"uOffset":0,"vOffset":0,"uScale":1,"vScale":-1,"uRotationCenter":0,"vRotationCenter":0,"wRotationCenter":0.5,"invertY":false,"uAng":0,"vAng":0,"wAng":0,"wrapU":1,"wrapV":1,"coordinatesIndex":0,"isRenderTarget":false,"renderTargetSize":0,"mirrorPlane":null,"renderList":null,"animations":[],"extensions":null,"samplingMode":3,"texture_id":"1599556231-7992c2e9"},"diffuseFresnelParameters":null,"ambientTexture":null,"opacityTexture":null,"opacityFresnelParameters":null,"reflectionTexture":null,"reflectionFresnelParameters":null,"emissiveTexture":null,"lightmapTexture":null,"useLightmapAsShadowmap":false,"emissiveFresnelParameters":null,"specularTexture":null,"bumpTexture":null,"useSpecularOverAlpha":true,"disableLighting":false,"useEmissiveAsIllumination":false,"linkEmissiveWithDiffuse":true,"twoSidedLighting":false,"maxSimultaneousLights":4,"useGlossinessFromSpecularMapAlpha":false,"name":"Material #37518","id":"ec871578-9f6b-4d46-b939-5872bf1f0fd1","backFaceCulling":true,"wireframe":false,"alpha":1,"alphaMode":2},"path":["1599556223-b4e09e09"]},"1599556231-afabfc7a":{"id":"1599556231-afabfc7a","type":"material","createdAt":"2020-09-08 17:10","modifiedAt":"2020-09-08 17:10","name":"Material #37519","preload":false,"has_thumbnail":false,"scope":{"type":"project","id":"a80566dc"},"file":null,"data":{"customType":"BABYLON.StandardMaterial","ambient":[1,1,1],"diffuse":[1,1,1],"specular":[0,0,0],"emissive":[0,0,0],"specularPower":25.6,"diffuseTexture":{"name":"t_1.jpg","level":1,"hasAlpha":true,"getAlphaFromRGB":false,"coordinatesMode":0,"isCube":false,"uOffset":0,"vOffset":0,"uScale":1,"vScale":-1,"uRotationCenter":0,"vRotationCenter":0,"wRotationCenter":0.5,"invertY":false,"uAng":0,"vAng":0,"wAng":0,"wrapU":1,"wrapV":1,"coordinatesIndex":0,"isRenderTarget":false,"renderTargetSize":0,"mirrorPlane":null,"renderList":null,"animations":[],"extensions":null,"samplingMode":3,"texture_id":"1599556231-bf26edb9"},"diffuseFresnelParameters":null,"ambientTexture":null,"opacityTexture":null,"opacityFresnelParameters":null,"reflectionTexture":null,"reflectionFresnelParameters":null,"emissiveTexture":null,"lightmapTexture":null,"useLightmapAsShadowmap":false,"emissiveFresnelParameters":null,"specularTexture":null,"bumpTexture":null,"useSpecularOverAlpha":true,"disableLighting":false,"useEmissiveAsIllumination":false,"linkEmissiveWithDiffuse":true,"twoSidedLighting":false,"maxSimultaneousLights":4,"useGlossinessFromSpecularMapAlpha":false,"name":"Material #37519","id":"db03fe9c-4e74-4b37-80db-64256f0b93a5","backFaceCulling":true,"wireframe":false,"alpha":1,"alphaMode":2},"path":["1599556223-b4e09e09"]},"1599556231-65b010f4":{"id":"1599556231-65b010f4","type":"material","createdAt":"2020-09-08 17:10","modifiedAt":"2020-09-08 17:10","name":"Material #2147448229","preload":false,"has_thumbnail":false,"scope":{"type":"project","id":"a80566dc"},"file":null,"data":{"customType":"BABYLON.StandardMaterial","ambient":[1,1,1],"diffuse":[1,1,1],"specular":[0,0,0],"emissive":[0,0,0],"specularPower":25.6,"diffuseTexture":{"name":"展厅XX主题 .png","level":1,"hasAlpha":true,"getAlphaFromRGB":false,"coordinatesMode":0,"isCube":false,"uOffset":0,"vOffset":0,"uScale":1,"vScale":-1,"uRotationCenter":0,"vRotationCenter":0,"wRotationCenter":0.5,"invertY":false,"uAng":0,"vAng":0,"wAng":0,"wrapU":1,"wrapV":1,"coordinatesIndex":0,"isRenderTarget":false,"renderTargetSize":0,"mirrorPlane":null,"renderList":null,"animations":[],"extensions":null,"samplingMode":3},"diffuseFresnelParameters":null,"ambientTexture":null,"opacityTexture":null,"opacityFresnelParameters":null,"reflectionTexture":null,"reflectionFresnelParameters":null,"emissiveTexture":null,"lightmapTexture":null,"useLightmapAsShadowmap":false,"emissiveFresnelParameters":null,"specularTexture":null,"bumpTexture":null,"useSpecularOverAlpha":true,"disableLighting":false,"useEmissiveAsIllumination":false,"linkEmissiveWithDiffuse":true,"twoSidedLighting":false,"maxSimultaneousLights":4,"useGlossinessFromSpecularMapAlpha":false,"name":"Material #2147448229","id":"b4b32d90-b143-458b-b9fc-9a647f17e273","backFaceCulling":true,"wireframe":false,"alpha":1,"alphaMode":2},"path":["1599556223-b4e09e09"]},"1599556231-f82f5737":{"id":"1599556231-f82f5737","type":"material","createdAt":"2020-09-08 17:10","modifiedAt":"2020-09-08 17:10","name":"画_10-16","preload":false,"has_thumbnail":false,"scope":{"type":"project","id":"a80566dc"},"file":null,"data":{"customType":"BABYLON.StandardMaterial","ambient":[1,1,1],"diffuse":[1,1,1],"specular":[0,0,0],"emissive":[0,0,0],"specularPower":25.6,"diffuseTexture":{"name":"展画.jpg","level":1,"hasAlpha":true,"getAlphaFromRGB":false,"coordinatesMode":0,"isCube":false,"uOffset":0,"vOffset":0,"uScale":1,"vScale":-1,"uRotationCenter":0,"vRotationCenter":0,"wRotationCenter":0.5,"invertY":false,"uAng":0,"vAng":0,"wAng":0,"wrapU":1,"wrapV":1,"coordinatesIndex":0,"isRenderTarget":false,"renderTargetSize":0,"mirrorPlane":null,"renderList":null,"animations":[],"extensions":null,"samplingMode":3,"texture_id":"1599556231-3154154c"},"diffuseFresnelParameters":null,"ambientTexture":null,"opacityTexture":null,"opacityFresnelParameters":null,"reflectionTexture":null,"reflectionFresnelParameters":null,"emissiveTexture":null,"lightmapTexture":null,"useLightmapAsShadowmap":false,"emissiveFresnelParameters":null,"specularTexture":null,"bumpTexture":null,"useSpecularOverAlpha":true,"disableLighting":false,"useEmissiveAsIllumination":false,"linkEmissiveWithDiffuse":true,"twoSidedLighting":false,"maxSimultaneousLights":4,"useGlossinessFromSpecularMapAlpha":false,"name":"画_10-16","id":"216484dc-9e8d-42f3-b01d-4b82d97a3b3c","backFaceCulling":true,"wireframe":false,"alpha":1,"alphaMode":2},"path":["1599556223-b4e09e09"]},"1599556231-e7a93b42":{"id":"1599556231-e7a93b42","type":"material","createdAt":"2020-09-08 17:10","modifiedAt":"2020-09-08 17:10","name":"16名称","preload":false,"has_thumbnail":false,"scope":{"type":"project","id":"a80566dc"},"file":null,"data":{"customType":"BABYLON.StandardMaterial","ambient":[1,1,1],"diffuse":[1,1,1],"specular":[0,0,0],"emissive":[0,0,0],"specularPower":25.6,"diffuseTexture":{"name":"标题.png","level":1,"hasAlpha":true,"getAlphaFromRGB":false,"coordinatesMode":0,"isCube":false,"uOffset":0,"vOffset":0,"uScale":1,"vScale":-1,"uRotationCenter":0,"vRotationCenter":0,"wRotationCenter":0.5,"invertY":false,"uAng":0,"vAng":0,"wAng":0,"wrapU":1,"wrapV":1,"coordinatesIndex":0,"isRenderTarget":false,"renderTargetSize":0,"mirrorPlane":null,"renderList":null,"animations":[],"extensions":null,"samplingMode":3,"texture_id":"1599556231-63e2ef8a"},"diffuseFresnelParameters":null,"ambientTexture":null,"opacityTexture":{"name":"10-16名称.png","level":1,"hasAlpha":true,"getAlphaFromRGB":false,"coordinatesMode":0,"isCube":false,"uOffset":0,"vOffset":0,"uScale":1,"vScale":-1,"uRotationCenter":0,"vRotationCenter":0,"wRotationCenter":0.5,"invertY":false,"uAng":0,"vAng":0,"wAng":0,"wrapU":1,"wrapV":1,"coordinatesIndex":0,"isRenderTarget":false,"renderTargetSize":0,"mirrorPlane":null,"renderList":null,"animations":[],"extensions":null,"samplingMode":3,"texture_id":"1599556231-4a198978"},"opacityFresnelParameters":null,"reflectionTexture":null,"reflectionFresnelParameters":null,"emissiveTexture":null,"lightmapTexture":null,"useLightmapAsShadowmap":false,"emissiveFresnelParameters":null,"specularTexture":null,"bumpTexture":null,"useSpecularOverAlpha":true,"disableLighting":false,"useEmissiveAsIllumination":false,"linkEmissiveWithDiffuse":true,"twoSidedLighting":false,"maxSimultaneousLights":4,"useGlossinessFromSpecularMapAlpha":false,"name":"16名称","id":"adc5b7c2-fbaa-44ed-a64a-567a52519692","backFaceCulling":true,"wireframe":false,"alpha":1,"alphaMode":2},"path":["1599556223-b4e09e09"]},"1599556231-3d748393":{"id":"1599556231-3d748393","type":"material","createdAt":"2020-09-08 17:10","modifiedAt":"2020-09-08 17:10","name":"Material #2147448150","preload":false,"has_thumbnail":false,"scope":{"type":"project","id":"a80566dc"},"file":null,"data":{"customType":"BABYLON.StandardMaterial","ambient":[0.3765,0.5059,0.5882],"diffuse":[0.3765,0.5059,0.5882],"specular":[0,0,0],"emissive":[0,0,0],"specularPower":25.6,"diffuseTexture":null,"diffuseFresnelParameters":null,"ambientTexture":null,"opacityTexture":null,"opacityFresnelParameters":null,"reflectionTexture":null,"reflectionFresnelParameters":null,"emissiveTexture":null,"lightmapTexture":null,"useLightmapAsShadowmap":false,"emissiveFresnelParameters":null,"specularTexture":null,"bumpTexture":null,"useSpecularOverAlpha":true,"disableLighting":false,"useEmissiveAsIllumination":false,"linkEmissiveWithDiffuse":true,"twoSidedLighting":false,"maxSimultaneousLights":4,"useGlossinessFromSpecularMapAlpha":false,"name":"Material #2147448150","id":"db5a01d2-421d-4cea-9074-4c22285d14c7","backFaceCulling":true,"wireframe":false,"alpha":0,"alphaMode":2},"path":["1599556223-b4e09e09"]},"1599556231-56ffc610":{"id":"1599556231-56ffc610","type":"material","createdAt":"2020-09-08 17:10","modifiedAt":"2020-09-08 17:10","name":"men","preload":false,"has_thumbnail":false,"scope":{"type":"project","id":"a80566dc"},"file":null,"data":{"customType":"BABYLON.StandardMaterial","ambient":[0.3765,0.5059,0.5882],"diffuse":[1,1,1],"specular":[0,0,0],"emissive":[0,0,0],"specularPower":25.6,"diffuseTexture":{"name":"men.png","level":1,"hasAlpha":true,"getAlphaFromRGB":false,"coordinatesMode":0,"isCube":false,"uOffset":0,"vOffset":0,"uScale":1,"vScale":-1,"uRotationCenter":0,"vRotationCenter":0,"wRotationCenter":0.5,"invertY":false,"uAng":0,"vAng":0,"wAng":0,"wrapU":1,"wrapV":1,"coordinatesIndex":0,"isRenderTarget":false,"renderTargetSize":0,"mirrorPlane":null,"renderList":null,"animations":[],"extensions":null,"samplingMode":3,"texture_id":"1599556231-e5de7b0f"},"diffuseFresnelParameters":null,"ambientTexture":null,"opacityTexture":null,"opacityFresnelParameters":null,"reflectionTexture":null,"reflectionFresnelParameters":null,"emissiveTexture":null,"lightmapTexture":null,"useLightmapAsShadowmap":false,"emissiveFresnelParameters":null,"specularTexture":null,"bumpTexture":null,"useSpecularOverAlpha":true,"disableLighting":false,"useEmissiveAsIllumination":false,"linkEmissiveWithDiffuse":true,"twoSidedLighting":false,"maxSimultaneousLights":4,"useGlossinessFromSpecularMapAlpha":false,"name":"men","id":"49de277a-c3b4-44c1-9ed1-fab4b0c9a5e8","backFaceCulling":true,"wireframe":false,"alpha":1,"alphaMode":2},"path":["1599556223-b4e09e09"]},"1599556231-9eade7bc":{"id":"1599556231-9eade7bc","type":"material","createdAt":"2020-09-08 17:10","modifiedAt":"2020-09-08 17:10","name":"透明玻璃","preload":false,"has_thumbnail":false,"scope":{"type":"project","id":"a80566dc"},"file":null,"data":{"customType":"BABYLON.StandardMaterial","ambient":[0.0784,0.0784,0.0784],"diffuse":[0.0784,0.0784,0.0784],"specular":[0,0,0],"emissive":[0,0,0],"specularPower":25.6,"diffuseTexture":null,"diffuseFresnelParameters":null,"ambientTexture":null,"opacityTexture":null,"opacityFresnelParameters":null,"reflectionTexture":null,"reflectionFresnelParameters":null,"emissiveTexture":null,"lightmapTexture":null,"useLightmapAsShadowmap":false,"emissiveFresnelParameters":null,"specularTexture":null,"bumpTexture":null,"useSpecularOverAlpha":true,"disableLighting":false,"useEmissiveAsIllumination":false,"linkEmissiveWithDiffuse":true,"twoSidedLighting":false,"maxSimultaneousLights":4,"useGlossinessFromSpecularMapAlpha":false,"name":"透明玻璃","id":"460162c2-4464-4997-991b-9b8bc47ef392","backFaceCulling":true,"wireframe":false,"alpha":0,"alphaMode":2},"path":["1599556223-b4e09e09"]},"1599556231-195a38d0":{"id":"1599556231-195a38d0","type":"material","createdAt":"2020-09-08 17:10","modifiedAt":"2020-09-08 17:10","name":"Material #6278","preload":false,"has_thumbnail":false,"scope":{"type":"project","id":"a80566dc"},"file":null,"data":{"customType":"BABYLON.StandardMaterial","ambient":[1,1,1],"diffuse":[1,1,1],"specular":[0,0,0],"emissive":[1,1,1],"specularPower":25.6,"diffuseTexture":null,"diffuseFresnelParameters":null,"ambientTexture":null,"opacityTexture":null,"opacityFresnelParameters":null,"reflectionTexture":null,"reflectionFresnelParameters":null,"emissiveTexture":null,"lightmapTexture":null,"useLightmapAsShadowmap":false,"emissiveFresnelParameters":null,"specularTexture":null,"bumpTexture":null,"useSpecularOverAlpha":true,"disableLighting":false,"useEmissiveAsIllumination":true,"linkEmissiveWithDiffuse":false,"twoSidedLighting":false,"maxSimultaneousLights":4,"useGlossinessFromSpecularMapAlpha":false,"name":"Material #6278","id":"73e53886-ec5a-4c39-b06f-ffdd5f9dd75d","backFaceCulling":true,"wireframe":false,"alpha":0,"alphaMode":2},"path":["1599556223-b4e09e09"]},"1599556231-bb8282c3":{"id":"1599556231-bb8282c3","type":"material","createdAt":"2020-09-08 17:10","modifiedAt":"2020-09-08 17:10","name":"Material #2147448218","preload":false,"has_thumbnail":false,"scope":{"type":"project","id":"a80566dc"},"file":null,"data":{"customType":"BABYLON.StandardMaterial","ambient":[1,1,1],"diffuse":[1,1,1],"specular":[0,0,0],"emissive":[0,0,0],"specularPower":25.6,"diffuseTexture":{"name":"lock.png","level":1,"hasAlpha":true,"getAlphaFromRGB":false,"coordinatesMode":0,"isCube":false,"uOffset":0,"vOffset":0,"uScale":1,"vScale":-1,"uRotationCenter":0,"vRotationCenter":0,"wRotationCenter":0.5,"invertY":false,"uAng":0,"vAng":0,"wAng":0,"wrapU":1,"wrapV":1,"coordinatesIndex":0,"isRenderTarget":false,"renderTargetSize":0,"mirrorPlane":null,"renderList":null,"animations":[],"extensions":null,"samplingMode":3,"texture_id":"1599556231-c18733cc"},"diffuseFresnelParameters":null,"ambientTexture":null,"opacityTexture":null,"opacityFresnelParameters":null,"reflectionTexture":null,"reflectionFresnelParameters":null,"emissiveTexture":null,"lightmapTexture":null,"useLightmapAsShadowmap":false,"emissiveFresnelParameters":null,"specularTexture":null,"bumpTexture":null,"useSpecularOverAlpha":true,"disableLighting":false,"useEmissiveAsIllumination":false,"linkEmissiveWithDiffuse":true,"twoSidedLighting":false,"maxSimultaneousLights":4,"useGlossinessFromSpecularMapAlpha":false,"name":"Material #2147448218","id":"5cb5574f-83b6-4749-8d19-f5a58a7521d2","backFaceCulling":true,"wireframe":false,"alpha":1,"alphaMode":2},"path":["1599556223-b4e09e09"]},"1599556231-5249d39a":{"id":"1599556231-5249d39a","type":"material","createdAt":"2020-09-08 17:10","modifiedAt":"2020-09-08 17:10","name":"Material #37494","preload":false,"has_thumbnail":false,"scope":{"type":"project","id":"a80566dc"},"file":null,"data":{"customType":"BABYLON.StandardMaterial","ambient":[1,1,1],"diffuse":[1,1,1],"specular":[0,0,0],"emissive":[0,0,0],"specularPower":25.6,"diffuseTexture":{"name":"对象184VRay完成贴图.jpg","level":1,"hasAlpha":true,"getAlphaFromRGB":false,"coordinatesMode":0,"isCube":false,"uOffset":0,"vOffset":0,"uScale":1,"vScale":-1,"uRotationCenter":0,"vRotationCenter":0,"wRotationCenter":0.5,"invertY":false,"uAng":0,"vAng":0,"wAng":0,"wrapU":1,"wrapV":1,"coordinatesIndex":0,"isRenderTarget":false,"renderTargetSize":0,"mirrorPlane":null,"renderList":null,"animations":[],"extensions":null,"samplingMode":3,"texture_id":"1599556231-66c8b544"},"diffuseFresnelParameters":null,"ambientTexture":null,"opacityTexture":null,"opacityFresnelParameters":null,"reflectionTexture":null,"reflectionFresnelParameters":null,"emissiveTexture":null,"lightmapTexture":null,"useLightmapAsShadowmap":false,"emissiveFresnelParameters":null,"specularTexture":null,"bumpTexture":null,"useSpecularOverAlpha":true,"disableLighting":false,"useEmissiveAsIllumination":false,"linkEmissiveWithDiffuse":true,"twoSidedLighting":false,"maxSimultaneousLights":4,"useGlossinessFromSpecularMapAlpha":false,"name":"Material #37494","id":"c0faf073-2dc8-43b3-b722-ba01c8a6279a","backFaceCulling":true,"wireframe":false,"alpha":1,"alphaMode":2},"path":["1599556223-b4e09e09"]},"1599556231-3154154c":{"id":"1599556231-3154154c","type":"texture","createdAt":"2020-09-08 17:10","modifiedAt":"2020-09-08 17:10","name":"展画.jpg","preload":"true","has_thumbnail":true,"scope":{"type":"project","id":"a80566dc"},"file":{"filename":"展画.jpg","size":1365831,"hash":"33467df275d97be10ad7b38a72f7360ffb729cff"},"data":null,"path":["1599556223-b4e09e09"]}},"geometry":{},"babylon":{"path":{"root":{"1599450148-8a725a25":true},"1599556223-b4e09e09":{"1599556231-4830bac7":true}},"1599450148-8a725a25":{"materials":{"db8b80e6-b96a-4916-902b-8278a716d828":{"asset_id":"1599450148-ac0936ff","diffuseTexture":"Line014VRay.jpg"},"abde4946-d763-453b-af3e-c11a5e2acab8":{"asset_id":"1599450148-4ee9e685","diffuseTexture":"对象199VRay完成贴图.jpg"},"33a181c9-5d4b-46a3-8f57-cd45ab54f380":{"asset_id":"1599450148-aed09ab7","diffuseTexture":"电脑.jpg"},"ec871578-9f6b-4d46-b939-5872bf1f0fd1":{"asset_id":"1599450148-a17af9d5","diffuseTexture":"001VRay完成贴图.jpg"},"db03fe9c-4e74-4b37-80db-64256f0b93a5":{"asset_id":"1599450148-880019e6","diffuseTexture":"t_1.jpg"},"b4b32d90-b143-458b-b9fc-9a647f17e273":{"asset_id":"1599450148-bc23834d","diffuseTexture":"展厅XX主题 .png"},"216484dc-9e8d-42f3-b01d-4b82d97a3b3c":{"asset_id":"1599450148-eb3c9d3b","diffuseTexture":"展画.jpg"},"adc5b7c2-fbaa-44ed-a64a-567a52519692":{"asset_id":"1599450148-ffada7f0","diffuseTexture":"标题.png","opacityTexture":"10-16名称.png"},"db5a01d2-421d-4cea-9074-4c22285d14c7":{"asset_id":"1599450148-427b03fe"},"49de277a-c3b4-44c1-9ed1-fab4b0c9a5e8":{"asset_id":"1599450148-6f74be2f","diffuseTexture":"men.png"},"460162c2-4464-4997-991b-9b8bc47ef392":{"asset_id":"1599450148-9a03d077"},"73e53886-ec5a-4c39-b06f-ffdd5f9dd75d":{"asset_id":"1599450148-d6986f0a"},"5cb5574f-83b6-4749-8d19-f5a58a7521d2":{"asset_id":"1599450148-2c6f003c","diffuseTexture":"lock.png"},"c0faf073-2dc8-43b3-b722-ba01c8a6279a":{"asset_id":"1599450148-daa74482","diffuseTexture":"对象184VRay完成贴图.jpg"}}},"1599556231-4830bac7":{"materials":{"db8b80e6-b96a-4916-902b-8278a716d828":{"asset_id":"1599556231-afee3f08","diffuseTexture":"Line014VRay.jpg"},"abde4946-d763-453b-af3e-c11a5e2acab8":{"asset_id":"1599556231-59fe6175","diffuseTexture":"对象199VRay完成贴图.jpg"},"33a181c9-5d4b-46a3-8f57-cd45ab54f380":{"asset_id":"1599556231-d11ba66a","diffuseTexture":"电脑.jpg"},"ec871578-9f6b-4d46-b939-5872bf1f0fd1":{"asset_id":"1599556231-1d616460","diffuseTexture":"001VRay完成贴图.jpg"},"db03fe9c-4e74-4b37-80db-64256f0b93a5":{"asset_id":"1599556231-afabfc7a","diffuseTexture":"t_1.jpg"},"b4b32d90-b143-458b-b9fc-9a647f17e273":{"asset_id":"1599556231-65b010f4","diffuseTexture":"展厅XX主题 .png"},"216484dc-9e8d-42f3-b01d-4b82d97a3b3c":{"asset_id":"1599556231-f82f5737","diffuseTexture":"展画.jpg"},"adc5b7c2-fbaa-44ed-a64a-567a52519692":{"asset_id":"1599556231-e7a93b42","diffuseTexture":"标题.png","opacityTexture":"10-16名称.png"},"db5a01d2-421d-4cea-9074-4c22285d14c7":{"asset_id":"1599556231-3d748393"},"49de277a-c3b4-44c1-9ed1-fab4b0c9a5e8":{"asset_id":"1599556231-56ffc610","diffuseTexture":"men.png"},"460162c2-4464-4997-991b-9b8bc47ef392":{"asset_id":"1599556231-9eade7bc"},"73e53886-ec5a-4c39-b06f-ffdd5f9dd75d":{"asset_id":"1599556231-195a38d0"},"5cb5574f-83b6-4749-8d19-f5a58a7521d2":{"asset_id":"1599556231-bb8282c3","diffuseTexture":"lock.png"},"c0faf073-2dc8-43b3-b722-ba01c8a6279a":{"asset_id":"1599556231-5249d39a","diffuseTexture":"对象184VRay完成贴图.jpg"}}}},"babylon_resource":{"root":{"1599450148-dbd9bca6":true,"1599450148-44cb5081":true,"1599450148-86e783d0":true,"1599450148-cab88031":true,"1599450148-a9f6fe16":true,"1599450148-f399ee19":true,"1599450148-f1a63b16":true,"1599450148-80c84be0":true,"1599450148-6d7963d8":true},"1599556223-b4e09e09":{"1599556231-4a198978":true,"1599556231-c18733cc":true,"1599556231-7992c2e9":true,"1599556231-bf26edb9":true,"1599556231-63e2ef8a":true,"1599556231-316f2e8d":true,"1599556231-e5de7b0f":true,"1599556231-66c8b544":true,"1599556231-3154154c":true}}}